.bumpversion.cfg
.compmake_history.txt
.gitignore
MANIFEST.in
Makefile
README.rst
example_app_compmake.py
pypackage.mk
requirements.txt
setup.py
.circleci/config.yml
attic/lenient_option_parser.py
attic/variations/__init__.py
attic/variations/old_code.py.old
attic/variations/unique_string.py
attic/variations/variations.py
attic/variations/variations_test.py
docs/.gitignore
docs/Makefile
docs/epydoc.cfg
docs/gitadd.zsh
docs/sphinxtogithub.py
docs/source/api.rst.inc
docs/source/api_reference.rst
docs/source/changelog.rst
docs/source/conf.py
docs/source/credits.rst
docs/source/definitions.txt
docs/source/download.html
docs/source/fork.html
docs/source/index.rst
docs/source/my_static/.empty
docs/source/my_templates/layout.html
src/QuickApp.egg-info/PKG-INFO
src/QuickApp.egg-info/SOURCES.txt
src/QuickApp.egg-info/dependency_links.txt
src/QuickApp.egg-info/entry_points.txt
src/QuickApp.egg-info/requires.txt
src/QuickApp.egg-info/top_level.txt
src/decent_params/__init__.py
src/decent_params/decent_param.py
src/decent_params/decent_params_imp.py
src/decent_params/decent_params_test.py
src/decent_params/exceptions.py
src/decent_params/utils/__init__.py
src/decent_params/utils/script_utils.py
src/quickapp/__init__.py
src/quickapp/compmake_context.py
src/quickapp/exceptions.py
src/quickapp/quick_app.py
src/quickapp/quick_app_base.py
src/quickapp/quick_multi_app.py
src/quickapp/report_manager.py
src/quickapp/resource_manager.py
src/quickapp/app_utils/__init__.py
src/quickapp/app_utils/minimal_name.py
src/quickapp/app_utils/subcontexts.py
src/quickapp/app_utils/subcontexts_test.py
src/quickapp/rm/__init__.py
src/quickapp/rm/configuration.py
src/quickapp/rm/create_index_dynamic.py
src/quickapp/rm/generated_report.py
src/quickapp/tests/.gitignore
src/quickapp/tests/__init__.py
src/quickapp/tests/example_recursive_reports.py
src/quickapp/tests/quickapp_test1.py
src/quickapp/tests/quickapp_test2.py
src/quickapp/tests/quickappbase.py
src/quickapp/tests/subcommands_test1.py
src/quickapp/tests/test_child_context.py
src/quickapp/tests/test_dynamic_1.py
src/quickapp/tests/test_dynamic_2_qa.py
src/quickapp/tests/test_dynamic_3_qa.py
src/quickapp/tests/test_dynamic_4_qa.py
