Metadata-Version: 1.1
Name: QuickApp
Version: 1.3.16
Summary: UNKNOWN
Home-page: http://github.com/AndreaCensi/quickapp
Author: Andrea Censi
Author-email: censi@mit.edu
License: UNKNOWN
Download-URL: http://github.com/AndreaCensi/quickapp/tarball/1.3.16
Platform: UNKNOWN
Classifier: Development Status :: 4 - Beta
